<?xml version="1.0" encoding="utf-8"?>

<profiles>
	<!-- name default is reserved for the standard profile -->
	<profile name="default" stencilset="stencilsets/bpmn2.0/bpmn2.0.json">
		<plugin source="toolbar.js" name="ORYX.Plugins.Toolbar" core="true" />
		<plugin name="ORYX.Plugins.File" source="file.js"/>
		<plugin name="ORYX.Plugins.SelectStencilSetPerspective" source="selectssperspective.js" />
		<plugin name="ORYX.Plugins.ShapeRepository" source="shaperepository.js"/>
		<plugin name="ORYX.Plugins.PropertyWindow" source="propertywindow.js"/>
		<plugin name="ORYX.Plugins.CanvasResize" source="canvasResize.js"/>
		<plugin name="ORYX.Plugins.View" source="view.js"/>
		<plugin name="ORYX.Plugins.DragDropResize" source="dragdropresize.js"/>
		<plugin name="ORYX.Plugins.RenameShapes" source="renameShapes.js" />
		<plugin name="ORYX.Plugins.JSONSupport" source="jsonSupport.js"/>
		<plugin name="ORYX.Plugins.Undo"  source="undo.js"/>		
		<plugin name="ORYX.Plugins.Arrangement" source="arrangement.js"/>
		<plugin name="ORYX.Plugins.Grouping"  source="grouping.js"/>	
		<plugin name="ORYX.Plugins.DragDocker"  source="dragDocker.js"/>	
		<plugin name="ORYX.Plugins.AddDocker"  source="addDocker.js"/>	
		<plugin name="ORYX.Plugins.SelectionFrame" source="selectionframe.js"/>	
		<plugin name="ORYX.Plugins.ShapeHighlighting" source="shapeHighlighting.js"/>	
		<plugin name="ORYX.Plugins.Edit" source="edit.js"/>	
		<plugin name="ORYX.Plugins.KeysMove" source="keysMove.js"/>	
		<plugin source="bpmn2.0/bpmn2.0.js" name="ORYX.Plugins.BPMN2_0"/>
		<plugin source="bpmn2.0/bpmn2conversation.js" name="ORYX.Plugins.BPMN2CONVERSATION"/>
		<plugin source="bpmn2.0/bpmn2.0choreography.js" name="ORYX.Plugins.Bpmn2_0Choreography"/>
		<plugin source="bpmn2.0/bpmn2.0serialization.js" name="ORYX.Plugins.BPMN2_0Serialization"/>
		
		<stencilsetextension namespace="http://oryx-editor.org/stencilsets/extensions/bpmncosts#"/>
	</profile>
</profiles>
